spyrmsd/__init__.py
spyrmsd/__main__.py
spyrmsd/constants.py
spyrmsd/due.py
spyrmsd/exceptions.py
spyrmsd/graph.py
spyrmsd/hungarian.py
spyrmsd/io.py
spyrmsd/molecule.py
spyrmsd/parallel.py
spyrmsd/qcp.py
spyrmsd/rmsd.py
spyrmsd/utils.py
spyrmsd/graphs/__init__.py
spyrmsd/graphs/_common.py
spyrmsd/graphs/gt.py
spyrmsd/graphs/nx.py
spyrmsd/graphs/rx.py
spyrmsd/optional/__init__.py
spyrmsd/optional/obabel.py
spyrmsd/optional/rdkit.py
spyrmsd-0.9.0.dist-info/licenses/LICENSE
spyrmsd-0.9.0.dist-info/WHEEL
spyrmsd-0.9.0.dist-info/METADATA
spyrmsd-0.9.0.dist-info/RECORD
