Metadata-Version: 2.4
Name: spyrmsd
Version: 0.9.0
Summary: Python RMSD tool with symmetry correction.
Home-page: https://spyrmsd.readthedocs.io
Author: Rocco Meli
Author-email: rocco.meli@cscs.ch
Requires-Python: >=3.9
Classifier: License :: OSI Approved :: MIT License
Classifier: Programming Language :: Python :: 3
License-File: LICENSE
Requires-Dist: numpy
Requires-Dist: scipy
Requires-Dist: rustworkx
